duckai/__init__.py
duckai/__main__.py
duckai/cli.py
duckai/duckai.py
duckai/exceptions.py
duckai/py.typed
duckai/utils.py
duckai/libs/utils_chat.cp313-win_amd64.pyd
duckai/libs/utils_chat__mypyc.cp313-win_amd64.pyd
duckai-0.3.1.dist-info/METADATA
duckai-0.3.1.dist-info/WHEEL
duckai-0.3.1.dist-info/entry_points.txt
duckai-0.3.1.dist-info/top_level.txt
duckai-0.3.1.dist-info/RECORD
