Metadata-Version: 2.4
Name: duckai
Version: 0.3.1
Summary: AI chat using the DuckDuckGo.com search engine
Author: deedy5
Project-URL: Homepage, https://github.com/deedy5/duckai
Classifier: Development Status :: 5 - Production/Stable
Classifier: Operating System :: OS Independent
Classifier: Programming Language :: Python :: 3
Classifier: Programming Language :: Python :: 3 :: Only
Classifier: Programming Language :: Python :: 3.9
Classifier: Programming Language :: Python :: 3.10
Classifier: Programming Language :: Python :: 3.11
Classifier: Programming Language :: Python :: 3.12
Classifier: Programming Language :: Python :: 3.13
Classifier: Programming Language :: Python :: Implementation :: CPython
Classifier: Topic :: Internet :: WWW/HTTP :: Indexing/Search
Classifier: Topic :: Software Development :: Libraries :: Python Modules
Requires-Python: >=3.9
Requires-Dist: click>=8.1.8
Requires-Dist: primp>=0.14.0
Requires-Dist: prompt-toolkit>=3.0.50
Requires-Dist: rich>=14.0.0
Requires-Dist: stpyv8>=13.1.201.22
Provides-Extra: dev
Requires-Dist: mypy[mypyc]>=1.15.0; extra == "dev"
Requires-Dist: orjson>=3.10.16; extra == "dev"
Requires-Dist: pytest>=8.3.4; extra == "dev"
Requires-Dist: ruff>=0.11.4; extra == "dev"
Requires-Dist: types-setuptools>=78.1.0.20250329; extra == "dev"
